bob/__init__.py
bob/io/__init__.py
bob/io/image.py
bob/io/base/__init__.py
bob/io/base/testing_utils.py
bob.io.base-5.1.1.dist-info/LICENSE
bob.io.base-5.1.1.dist-info/METADATA
bob.io.base-5.1.1.dist-info/WHEEL
bob.io.base-5.1.1.dist-info/top_level.txt
bob.io.base-5.1.1.dist-info/zip-safe
bob.io.base-5.1.1.dist-info/RECORD
