Metadata-Version: 2.1
Name: bob.io.base
Version: 5.1.1
Summary: Basic IO for Bob
Author-email: Andre Anjos <andre.anjos@idiap.ch>
License: BSD 3-Clause License
Project-URL: documentation, https://www.idiap.ch/software/bob/docs/bob/bob.io.base/v5.1.1/sphinx
Project-URL: homepage, https://pypi.org/project/bob.io.base
Project-URL: repository, https://gitlab.idiap.ch/bob/bob.io.base
Project-URL: changelog, https://gitlab.idiap.ch/bob/bob.io.base/-/releases
Classifier: Development Status :: 4 - Beta
Classifier: Intended Audience :: Developers
Classifier: License :: OSI Approved :: BSD License
Classifier: Natural Language :: English
Classifier: Programming Language :: Python :: 3
Classifier: Topic :: Software Development :: Libraries :: Python Modules
Requires-Python: >=3.9
License-File: LICENSE
Requires-Dist: bob ==12.1.1
Requires-Dist: h5py ~=3.7
Requires-Dist: imageio ~=2.34
Requires-Dist: numpy ~=1.26
Requires-Dist: pillow ~=10.2
Provides-Extra: doc
Requires-Dist: sphinx ; extra == 'doc'
Requires-Dist: sphinx-rtd-theme ; extra == 'doc'
Requires-Dist: auto-intersphinx ; extra == 'doc'
Provides-Extra: qa
Requires-Dist: pre-commit ; extra == 'qa'
Provides-Extra: test
Requires-Dist: pytest ; extra == 'test'
Requires-Dist: pytest-cov ; extra == 'test'
Requires-Dist: coverage ; extra == 'test'
